MAOuladrocket/MAOuladrocket.py
MAOuladrocket/__init__.py
rocket/MAOuladrocket.py
rocket/__init__.py
rocket/my_rocket.py
MAOuladrocket-1.0.0.dist-info/LICENSE.txt
MAOuladrocket-1.0.0.dist-info/METADATA
MAOuladrocket-1.0.0.dist-info/WHEEL
MAOuladrocket-1.0.0.dist-info/top_level.txt
MAOuladrocket-1.0.0.dist-info/RECORD
