Metadata-Version: 2.1
Name: MAOuladrocket
Version: 1.0.0
Summary: An awesome package that does something
Home-page: http://pypi.python.org/pypi/MAOuladrocket/
Author: Mohamed lamine OULAD SAID
Author-email: mohamedamineouledsaid10@gmail.com
License: LICENSE.txt
License-File: LICENSE.txt
